sqlite_utils_sqlite_xl/__init__.py
sqlite_utils_sqlite_xl-0.0.1a4.dist-info/METADATA
sqlite_utils_sqlite_xl-0.0.1a4.dist-info/WHEEL
sqlite_utils_sqlite_xl-0.0.1a4.dist-info/entry_points.txt
sqlite_utils_sqlite_xl-0.0.1a4.dist-info/top_level.txt
sqlite_utils_sqlite_xl-0.0.1a4.dist-info/RECORD
